{"results": [{"val": [966], "param": "vlan0-in"}, {"val": [0], "param": "vlan0-out"}, {"val": [504], "param": "vlan1-in"}, {"val": [0], "param": "vlan1-out"}, {"val": [462], "param": "vlan2-in"}, {"val": [0], "param": "vlan2-out"}, {"val": [1624556], "param": "vlan3-in"}, {"val": [1429262], "param": "vlan3-out"}, {"val": [504], "param": "vlan4-in"}, {"val": [0], "param": "vlan4-out"}, {"val": [462], "param": "vlan5-in"}, {"val": [0], "param": "vlan5-out"}, {"val": [966], "param": "vlan6-in"}, {"val": [0], "param": "vlan6-out"}]}